nonebot_plugin_arcaeabot/__init__.py
nonebot_plugin_arcaeabot/api/__init__.py
nonebot_plugin_arcaeabot/api/request.py
nonebot_plugin_arcaeabot/assets_updater.py
nonebot_plugin_arcaeabot/config.py
nonebot_plugin_arcaeabot/database.py
nonebot_plugin_arcaeabot/handler/__init__.py
nonebot_plugin_arcaeabot/handler/assets_update.py
nonebot_plugin_arcaeabot/handler/b30.py
nonebot_plugin_arcaeabot/handler/best.py
nonebot_plugin_arcaeabot/handler/bind.py
nonebot_plugin_arcaeabot/handler/defualt.py
nonebot_plugin_arcaeabot/handler/help.py
nonebot_plugin_arcaeabot/handler/info.py
nonebot_plugin_arcaeabot/handler/pre.py
nonebot_plugin_arcaeabot/handler/preview.py
nonebot_plugin_arcaeabot/handler/random.py
nonebot_plugin_arcaeabot/handler/recent.py
nonebot_plugin_arcaeabot/handler/song.py
nonebot_plugin_arcaeabot/matcher.py
nonebot_plugin_arcaeabot/message/__init__.py
nonebot_plugin_arcaeabot/message/image_message/__init__.py
nonebot_plugin_arcaeabot/message/image_message/best_30/__init__.py
nonebot_plugin_arcaeabot/message/image_message/best_30/chieri_style.py
nonebot_plugin_arcaeabot/message/image_message/single_song/__init__.py
nonebot_plugin_arcaeabot/message/image_message/single_song/andreal_style_v3.py
nonebot_plugin_arcaeabot/message/image_message/utils.py
nonebot_plugin_arcaeabot/message/text_message/__init__.py
nonebot_plugin_arcaeabot/resource/b30/B30.png
nonebot_plugin_arcaeabot/resource/b30/Divider.png
nonebot_plugin_arcaeabot/resource/b30/mask.png
nonebot_plugin_arcaeabot/resource/b30/table.png
nonebot_plugin_arcaeabot/resource/diff/BYD.png
nonebot_plugin_arcaeabot/resource/diff/FTR.png
nonebot_plugin_arcaeabot/resource/diff/PRS.png
nonebot_plugin_arcaeabot/resource/diff/PST.png
nonebot_plugin_arcaeabot/resource/font/Andrea.otf
nonebot_plugin_arcaeabot/resource/font/Exo-Medium.ttf
nonebot_plugin_arcaeabot/resource/font/Exo-Regular.ttf
nonebot_plugin_arcaeabot/resource/font/Exo-SemiBold.ttf
nonebot_plugin_arcaeabot/resource/font/Kazesawa-Regular.ttf
nonebot_plugin_arcaeabot-3.0.9.dist-info/WHEEL
nonebot_plugin_arcaeabot-3.0.9.dist-info/METADATA
nonebot_plugin_arcaeabot-3.0.9.dist-info/RECORD
