Metadata-Version: 2.1
Name: nonebot-plugin-arcaeabot
Version: 3.0.9
Summary: An arcaea plugin for nonebot2. ( A cross platform Python async bot framework. )
Home-page: https://github.com/SEAFHMC/nonebot-plugin-arcaeabot
License: AGPL-3.0 License
Author: SEAFHMC
Author-email: soku_ritsuki@outlook.com
Requires-Python: >=3.8,<4.0
Classifier: License :: Other/Proprietary License
Classifier: Programming Language :: Python :: 3
Classifier: Programming Language :: Python :: 3.10
Classifier: Programming Language :: Python :: 3.8
Classifier: Programming Language :: Python :: 3.9
Requires-Dist: Pillow (>=8.3.1)
Requires-Dist: httpx (>=0.20.0,<1.0.0)
Requires-Dist: nonebot-adapter-onebot (>=2.1.1,<3.0.0)
Requires-Dist: nonebot2 (>=2.0.0-beta.4,<3.0.0)
Requires-Dist: peewee (>=3.14.4)
Requires-Dist: ruamel.yaml (>=0.17.2,<0.18.0)
Requires-Dist: tqdm (>=4.1.0,<5.0.0)
Project-URL: Documentation, https://github.com/SEAFHMC/nonebot-plugin-arcaeabot/blob/v3.0.0/README.md
Project-URL: Repository, https://github.com/SEAFHMC/nonebot-plugin-arcaeabot
